fx_analytics/__init__.py
fx_analytics/app.py
fx_analytics/config.py
fx_analytics/credential.py
fx_analytics/main_functions.py
fx_analytics/test_read_df.py
fx_analytics-1.6.5.dist-info/LICENSE
fx_analytics-1.6.5.dist-info/METADATA
fx_analytics-1.6.5.dist-info/WHEEL
fx_analytics-1.6.5.dist-info/top_level.txt
fx_analytics-1.6.5.dist-info/RECORD
