Metadata-Version: 2.1
Name: fx-analytics
Version: 1.6.5
Home-page: https://github.com/jaybfn/fx_analytics
Author: Jayesh Arun Bafna
Author-email: jayesh.bfn@gmail.com
License: MIT
Requires-Python: >=3.11
License-File: LICENSE
Requires-Dist: pandas >=2.1.0
Requires-Dist: streamlit >=1.26.0
Requires-Dist: plotly >=5.16.1
Requires-Dist: plotly-express >=0.4.1
Requires-Dist: loguru >=0.7.2
Requires-Dist: wheel
Requires-Dist: pytest
Provides-Extra: dev
Requires-Dist: pytest ; extra == 'dev'
Requires-Dist: twine ; extra == 'dev'
